pytwitterscraper/__init__.py
pytwitterscraper/scraper.py
pytwitterscraper/scraperresult.py
pytwitterscraper/user_agent.json
pytwitterscraper/woeid.json
pytwitterscraper-1.3.5.dist-info/LICENSE
pytwitterscraper-1.3.5.dist-info/METADATA
pytwitterscraper-1.3.5.dist-info/WHEEL
pytwitterscraper-1.3.5.dist-info/top_level.txt
pytwitterscraper-1.3.5.dist-info/RECORD
