Metadata-Version: 2.1
Name: pytwitterscraper
Version: 1.3.5
Summary: Twitter Scraper using Python
Home-page: https://github.com/mrwan200/pytwitterscraper
Author: M-307
Author-email: contact@m-307.tk
License: UNKNOWN
Keywords: pytwitterscraper,twitterscraper,webscraper,apiscraper
Platform: UNKNOWN
Classifier: Programming Language :: Python :: 3
Classifier: License :: OSI Approved :: MIT License
Classifier: Operating System :: OS Independent
Requires-Python: >=3.6
Requires-Dist: appdirs (==1.4.4)
Requires-Dist: beautifulsoup4 (==4.9.3)
Requires-Dist: bs4 (==0.0.1)
Requires-Dist: certifi (==2020.12.5)
Requires-Dist: chardet (==3.0.4)
Requires-Dist: cssselect (==1.1.0)
Requires-Dist: fake-useragent (==0.1.11)
Requires-Dist: idna (==2.10)
Requires-Dist: lxml (==4.6.2)
Requires-Dist: parse (==1.18.0)
Requires-Dist: pyee (==7.0.4)
Requires-Dist: pyppeteer (==0.2.2)
Requires-Dist: pyquery (==1.4.3)
Requires-Dist: requests (==2.25.0)
Requires-Dist: requests-html (==0.10.0)
Requires-Dist: six (==1.15.0)
Requires-Dist: soupsieve (==2.1)
Requires-Dist: tqdm (==4.54.1)
Requires-Dist: urllib3 (==1.26.2)
Requires-Dist: w3lib (==1.22.0)
Requires-Dist: websockets (==8.1)
